Metadata-Version: 1.0
Name: dsbws-probability
Version: 1.0
Summary: Gaussian and Binomial distributions
Home-page: UNKNOWN
Author: Arturo Brokate
Author-email: UNKNOWN
License: UNKNOWN
Platform: UNKNOWN
